vector_cache/__init__.py
vector_cache/core.py
vector_cache/version.py
vector_cache/bin/db_server_darwin_amd64
vector_cache/bin/db_server_linux_amd64
vector_cache_memory-0.1.6.dist-info/METADATA
vector_cache_memory-0.1.6.dist-info/WHEEL
vector_cache_memory-0.1.6.dist-info/top_level.txt
vector_cache_memory-0.1.6.dist-info/RECORD
