Metadata-Version: 2.4
Name: vector-cache-memory
Version: 0.1.6
Summary: Python client for VectorCache Go DB server
Author-email: Abhishek Maurya <abhishekmaurya.official@gmail.com>
Project-URL: Homepage, https://github.com/vector-cache/vector-cache
Requires-Python: >=3.9
Requires-Dist: requests>=2.30.0
Requires-Dist: setuptools_scm>=7.1
